{"projectName": "Proje 2 Not Tablosu", "tasks": [{"name": "1", "out": "", "err": "", "ref_out": "", "ref_err": "", "pass": true, "points": 10, "timeout": false}, {"name": "2", "out": "ID                  Parent ID           Command                                           \n====                =========           ========                                          \n2006724             2006723             ./main                                            \n2006723             2006722             timeout                                           \n2006722             2002759             /bin/bash                                         \n2002759             1154920             python                                            \n1154920             54808               /bin/bash                                         \n54808               2029                /usr/bin/konsole                                  \n2029                1710                /usr/bin/plasmashell                              \n1710                1                   /usr/lib/systemd/systemd                          \n1                   0                   /usr/lib/systemd/systemd                          \n", "err": "", "ref_out": "ID                  Parent ID           Command                                           \n2007762             2007761             ./main                                            \n2007761             2007760             timeout                                           \n2007760             2002759             /bin/bash                                         \n2002759             1154920             python                                            \n1154920             54808               /bin/bash                                         \n54808               2029                /usr/bin/konsole                                  \n2029                1710                /usr/bin/plasmashell                              \n1710                1                   /usr/lib/systemd/systemd                          \n1                   0                   /usr/lib/systemd/systemd                          \n", "ref_err": "", "pass": true, "points": 45, "timeout": false}, {"name": "3", "out": "ID                  Parent ID           Command                                           \n====                =========           ========                                          \n2006727             2006726             ./main                                            \n2006726             2006725             timeout                                           \n2006725             2002759             /bin/bash                                         \n2002759             1154920             python                                            \n1154920             54808               /bin/bash                                         \n54808               2029                /usr/bin/konsole                                  \n2029                1710                /usr/bin/plasmashell                              \n1710                1                   /usr/lib/systemd/systemd                          \n1                   0                   /usr/lib/systemd/systemd                          \n", "err": "", "ref_out": "ID                  Parent ID           Command                                           \n2007765             2007764             ./main                                            \n2007764             2007763             timeout                                           \n2007763             2002759             /bin/bash                                         \n2002759             1154920             python                                            \n1154920             54808               /bin/bash                                         \n54808               2029                /usr/bin/konsole                                  \n2029                1710                /usr/bin/plasmashell                              \n1710                1                   /usr/lib/systemd/systemd                          \n1                   0                   /usr/lib/systemd/systemd                          \n", "ref_err": "", "pass": true, "points": 45, "timeout": false}, {"name": "4", "out": "ID                  Parent ID           Command                                           \n====                =========           ========                                          \n2006730             2006729             ./main                                            \n2006729             2006728             timeout                                           \n2006728             2002759             /bin/bash                                         \n2002759             1154920             python                                            \n1154920             54808               /bin/bash                                         \n54808               2029                /usr/bin/konsole                                  \n2029                1710                /usr/bin/plasmashell                              \n1710                1                   /usr/lib/systemd/systemd                          \n1                   0                   /usr/lib/systemd/systemd                          \n", "err": "", "ref_out": "ID                  Parent ID           Command                                           \n2007768             2007767             ./main                                            \n2007767             2007766             timeout                                           \n2007766             2002759             /bin/bash                                         \n2002759             1154920             python                                            \n1154920             54808               /bin/bash                                         \n54808               2029                /usr/bin/konsole                                  \n2029                1710                /usr/bin/plasmashell                              \n1710                1                   /usr/lib/systemd/systemd                          \n1                   0                   /usr/lib/systemd/systemd                          \n", "ref_err": "", "pass": false, "points": 0, "timeout": false}, {"name": "5", "out": "ID                  Parent ID           Command                                           \n====                =========           ========                                          \n2006734             2006733             ./main                                            \n2006733             2006732             timeout                                           \n2006732             2006731             perf                                              \n2006731             2002759             /bin/bash                                         \n2002759             1154920             python                                            \n1154920             54808               /bin/bash                                         \n54808               2029                /usr/bin/konsole                                  \n2029                1710                /usr/bin/plasmashell                              \n1710                1                   /usr/lib/systemd/systemd                          \n1                   0                   /usr/lib/systemd/systemd                          \nID                  Parent ID           Command                                           \n====                =========           ========                                          \n2006736             2006735             ./main                                            \n2006735             2006732             timeout                                           \n2006732             2006731             perf                                              \n2006731             2002759             /bin/bash                                         \n2002759             1154920             python                                            \n1154920             54808               /bin/bash                                         \n54808               2029                /usr/bin/konsole                                  \n2029                1710                /usr/bin/plasmashell                              \n1710                1                   /usr/lib/systemd/systemd                          \n1                   0                   /usr/lib/systemd/systemd                          \nID                  Parent ID           Command                                           \n====                =========           ========                                          \n2006738             2006737             ./main                                            \n2006737             2006732             timeout                                           \n2006732             2006731             perf                                              \n2006731             2002759             /bin/bash                                         \n2002759             1154920             python                                            \n1154920             54808               /bin/bash                                         \n54808               2029                /usr/bin/konsole                                  \n2029                1710                /usr/bin/plasmashell                              \n1710                1                   /usr/lib/systemd/systemd                          \n1                   0                   /usr/lib/systemd/systemd                          \nID                  Parent ID           Command                                           \n====                =========           ========                                          \n2006740             2006739             ./main                                            \n2006739             2006732             timeout                                           \n2006732             2006731             perf                                              \n2006731             2002759             /bin/bash                                         \n2002759             1154920             python                                            \n1154920             54808               /bin/bash                                         \n54808               2029                /usr/bin/konsole                                  \n2029                1710                /usr/bin/plasmashell                              \n1710                1                   /usr/lib/systemd/systemd                          \n1                   0                   /usr/lib/systemd/systemd                          \nID                  Parent ID           Command                                           \n====                =========           ========                                          \n2006742             2006741             ./main                                            \n2006741             2006732             timeout                                           \n2006732             2006731             perf                                              \n2006731             2002759             /bin/bash                                         \n2002759             1154920             python                                            \n1154920             54808               /bin/bash                                         \n54808               2029                /usr/bin/konsole                                  \n2029                1710                /usr/bin/plasmashell                              \n1710                1                   /usr/lib/systemd/systemd                          \n1                   0                   /usr/lib/systemd/systemd                          \nID                  Parent ID           Command                                           \n====                =========           ========                                          \n2006744             2006743             ./main                                            \n2006743             2006732             timeout                                           \n2006732             2006731             perf                                              \n2006731             2002759             /bin/bash                                         \n2002759             1154920             python                                            \n1154920             54808               /bin/bash                                         \n54808               2029                /usr/bin/konsole                                  \n2029                1710                /usr/bin/plasmashell                              \n1710                1                   /usr/lib/systemd/systemd                          \n1                   0                   /usr/lib/systemd/systemd                          \nID                  Parent ID           Command                                           \n====                =========           ========                                          \n2006746             2006745             ./main                                            \n2006745             2006732             timeout                                           \n2006732             2006731             perf                                              \n2006731             2002759             /bin/bash                                         \n2002759             1154920             python                                            \n1154920             54808               /bin/bash                                         \n54808               2029                /usr/bin/konsole                                  \n2029                1710                /usr/bin/plasmashell                              \n1710                1                   /usr/lib/systemd/systemd                          \n1                   0                   /usr/lib/systemd/systemd                          \nID                  Parent ID           Command                                           \n====                =========           ========                                          \n2006748             2006747             ./main                                            \n2006747             2006732             timeout                                           \n2006732             2006731             perf                                              \n2006731             2002759             /bin/bash                                         \n2002759             1154920             python                                            \n1154920             54808               /bin/bash                                         \n54808               2029                /usr/bin/konsole                                  \n2029                1710                /usr/bin/plasmashell                              \n1710                1                   /usr/lib/systemd/systemd                          \n1                   0                   /usr/lib/systemd/systemd                          \nID                  Parent ID           Command                                           \n====                =========           ========                                          \n2006750             2006749             ./main                                            \n2006749             2006732             timeout                                           \n2006732             2006731             perf                                              \n2006731             2002759             /bin/bash                                         \n2002759             1154920             python                                            \n1154920             54808               /bin/bash                                         \n54808               2029                /usr/bin/konsole                                  \n2029                1710                /usr/bin/plasmashell                              \n1710                1                   /usr/lib/systemd/systemd                          \n1                   0                   /usr/lib/systemd/systemd                          \nID                  Parent ID           Command                                           \n====                =========           ========                                          \n2006752             2006751             ./main                                            \n2006751             2006732             timeout                                           \n2006732             2006731             perf                                              \n2006731             2002759             /bin/bash                                         \n2002759             1154920             python                                            \n1154920             54808               /bin/bash                                         \n54808               2029                /usr/bin/konsole                                  \n2029                1710                /usr/bin/plasmashell                              \n1710                1                   /usr/lib/systemd/systemd                          \n1                   0                   /usr/lib/systemd/systemd                          \n", "err": "\n Performance counter stats for 'timeout 0.2 stdbuf -o0 ./main' (10 runs):\n\n              2.44 msec task-clock                       #    0.746 CPUs utilized            ( +-  2.65% )\n                 1      context-switches                 #  388.656 /sec                     ( +- 22.11% )\n                 0      cpu-migrations                   #    0.000 /sec                   \n               235      page-faults                      #   91.334 K/sec                    ( +-  0.32% )\n         4,398,648      cycles                           #    1.710 GHz                      ( +-  2.54% )\n         4,982,472      instructions                     #    1.09  insn per cycle           ( +-  0.26% )\n         1,116,831      branches                         #  434.063 M/sec                    ( +-  0.27% )\n            22,657      branch-misses                    #    2.00% of all branches          ( +-  2.52% )\n        21,993,240      slots                            #    8.548 G/sec                    ( +-  2.08% )\n         5,456,871      topdown-retiring                 #     25.2% Retiring                ( +-  0.27% )\n         2,144,574      topdown-bad-spec                 #     10.0% Bad Speculation         ( +-  1.90% )\n         7,798,818      topdown-fe-bound                 #     36.3% Frontend Bound          ( +-  1.51% )\n         6,592,972      topdown-be-bound                 #     28.5% Backend Bound           ( +-  5.13% )\n         1,297,332      L1-dcache-loads                  #  504.215 M/sec                    ( +-  0.28% )\n            70,013      L1-dcache-load-misses            #    5.32% of all L1-dcache accesses  ( +-  1.16% )\n             9,444      LLC-loads                        #    3.670 M/sec                    ( +-  3.09% )\n               238      LLC-load-misses                  #    2.37% of all LL-cache accesses  ( +- 58.77% )\n\n         0.0032786 +- 0.0000726 seconds time elapsed  ( +-  2.22% )\n\n", "ref_out": "ID                  Parent ID           Command                                           \n2007772             2007771             ./main                                            \n2007771             2007770             timeout                                           \n2007770             2007769             perf                                              \n2007769             2002759             /bin/bash                                         \n2002759             1154920             python                                            \n1154920             54808               /bin/bash                                         \n54808               2029                /usr/bin/konsole                                  \n2029                1710                /usr/bin/plasmashell                              \n1710                1                   /usr/lib/systemd/systemd                          \n1                   0                   /usr/lib/systemd/systemd                          \nID                  Parent ID           Command                                           \n2007774             2007773             ./main                                            \n2007773             2007770             timeout                                           \n2007770             2007769             perf                                              \n2007769             2002759             /bin/bash                                         \n2002759             1154920             python                                            \n1154920             54808               /bin/bash                                         \n54808               2029                /usr/bin/konsole                                  \n2029                1710                /usr/bin/plasmashell                              \n1710                1                   /usr/lib/systemd/systemd                          \n1                   0                   /usr/lib/systemd/systemd                          \nID                  Parent ID           Command                                           \n2007776             2007775             ./main                                            \n2007775             2007770             timeout                                           \n2007770             2007769             perf                                              \n2007769             2002759             /bin/bash                                         \n2002759             1154920             python                                            \n1154920             54808               /bin/bash                                         \n54808               2029                /usr/bin/konsole                                  \n2029                1710                /usr/bin/plasmashell                              \n1710                1                   /usr/lib/systemd/systemd                          \n1                   0                   /usr/lib/systemd/systemd                          \nID                  Parent ID           Command                                           \n2007778             2007777             ./main                                            \n2007777             2007770             timeout                                           \n2007770             2007769             perf                                              \n2007769             2002759             /bin/bash                                         \n2002759             1154920             python                                            \n1154920             54808               /bin/bash                                         \n54808               2029                /usr/bin/konsole                                  \n2029                1710                /usr/bin/plasmashell                              \n1710                1                   /usr/lib/systemd/systemd                          \n1                   0                   /usr/lib/systemd/systemd                          \nID                  Parent ID           Command                                           \n2007780             2007779             ./main                                            \n2007779             2007770             timeout                                           \n2007770             2007769             perf                                              \n2007769             2002759             /bin/bash                                         \n2002759             1154920             python                                            \n1154920             54808               /bin/bash                                         \n54808               2029                /usr/bin/konsole                                  \n2029                1710                /usr/bin/plasmashell                              \n1710                1                   /usr/lib/systemd/systemd                          \n1                   0                   /usr/lib/systemd/systemd                          \nID                  Parent ID           Command                                           \n2007782             2007781             ./main                                            \n2007781             2007770             timeout                                           \n2007770             2007769             perf                                              \n2007769             2002759             /bin/bash                                         \n2002759             1154920             python                                            \n1154920             54808               /bin/bash                                         \n54808               2029                /usr/bin/konsole                                  \n2029                1710                /usr/bin/plasmashell                              \n1710                1                   /usr/lib/systemd/systemd                          \n1                   0                   /usr/lib/systemd/systemd                          \nID                  Parent ID           Command                                           \n2007784             2007783             ./main                                            \n2007783             2007770             timeout                                           \n2007770             2007769             perf                                              \n2007769             2002759             /bin/bash                                         \n2002759             1154920             python                                            \n1154920             54808               /bin/bash                                         \n54808               2029                /usr/bin/konsole                                  \n2029                1710                /usr/bin/plasmashell                              \n1710                1                   /usr/lib/systemd/systemd                          \n1                   0                   /usr/lib/systemd/systemd                          \nID                  Parent ID           Command                                           \n2007786             2007785             ./main                                            \n2007785             2007770             timeout                                           \n2007770             2007769             perf                                              \n2007769             2002759             /bin/bash                                         \n2002759             1154920             python                                            \n1154920             54808               /bin/bash                                         \n54808               2029                /usr/bin/konsole                                  \n2029                1710                /usr/bin/plasmashell                              \n1710                1                   /usr/lib/systemd/systemd                          \n1                   0                   /usr/lib/systemd/systemd                          \nID                  Parent ID           Command                                           \n2007788             2007787             ./main                                            \n2007787             2007770             timeout                                           \n2007770             2007769             perf                                              \n2007769             2002759             /bin/bash                                         \n2002759             1154920             python                                            \n1154920             54808               /bin/bash                                         \n54808               2029                /usr/bin/konsole                                  \n2029                1710                /usr/bin/plasmashell                              \n1710                1                   /usr/lib/systemd/systemd                          \n1                   0                   /usr/lib/systemd/systemd                          \nID                  Parent ID           Command                                           \n2007790             2007789             ./main                                            \n2007789             2007770             timeout                                           \n2007770             2007769             perf                                              \n2007769             2002759             /bin/bash                                         \n2002759             1154920             python                                            \n1154920             54808               /bin/bash                                         \n54808               2029                /usr/bin/konsole                                  \n2029                1710                /usr/bin/plasmashell                              \n1710                1                   /usr/lib/systemd/systemd                          \n1                   0                   /usr/lib/systemd/systemd                          \n", "ref_err": "\n Performance counter stats for 'timeout 0.2 stdbuf -o0 ./main' (10 runs):\n\n              2.29 msec task-clock                       #    0.719 CPUs utilized            ( +-  2.11% )\n                 2      context-switches                 #  806.897 /sec                     ( +-  6.67% )\n                 0      cpu-migrations                   #    0.000 /sec                   \n               238      page-faults                      #   96.021 K/sec                    ( +-  0.24% )\n         4,166,609      cycles                           #    1.681 GHz                      ( +-  1.72% )\n         5,062,914      instructions                     #    1.15  insn per cycle           ( +-  0.13% )\n         1,135,146      branches                         #  457.973 M/sec                    ( +-  0.14% )\n            19,991      branch-misses                    #    1.77% of all branches          ( +-  3.30% )\n        20,628,165      slots                            #    8.322 G/sec                    ( +-  1.38% )\n         5,501,117      topdown-retiring                 #     25.8% Retiring                ( +-  0.15% )\n         1,933,302      topdown-bad-spec                 #      9.8% Bad Speculation         ( +-  2.33% )\n         7,426,248      topdown-fe-bound                 #     36.8% Frontend Bound          ( +-  1.39% )\n         5,767,495      topdown-be-bound                 #     27.6% Backend Bound           ( +-  3.19% )\n         1,320,237      L1-dcache-loads                  #  532.648 M/sec                    ( +-  0.14% )\n            69,709      L1-dcache-load-misses            #    5.31% of all L1-dcache accesses  ( +-  0.93% )\n             9,524      LLC-loads                        #    3.842 M/sec                    ( +-  2.20% )\n               187      LLC-load-misses                  #    1.90% of all LL-cache accesses  ( +-128.16% )\n\n         0.0031790 +- 0.0000597 seconds time elapsed  ( +-  1.88% )\n\n", "pass": true, "points": 0, "timeout": false}]}